amulet/__init__.py
amulet/_version.py
amulet/__pyinstaller/__init__.py
amulet/__pyinstaller/hook-amulet.py
amulet/api/__init__.py
amulet/api/abstract_base_entity.py
amulet/api/block.py
amulet/api/block_entity.py
amulet/api/cache.py
amulet/api/entity.py
amulet/api/errors.py
amulet/api/item.py
amulet/api/player.py
amulet/api/structure.py
amulet/api/chunk/__init__.py
amulet/api/chunk/biomes.py
amulet/api/chunk/block_entity_dict.py
amulet/api/chunk/blocks.py
amulet/api/chunk/chunk.py
amulet/api/chunk/entity_list.py
amulet/api/chunk/status.py
amulet/api/data_types/__init__.py
amulet/api/data_types/generic_types.py
amulet/api/data_types/operation_types.py
amulet/api/data_types/world_types.py
amulet/api/data_types/wrapper_types.py
amulet/api/history/__init__.py
amulet/api/history/changeable.py
amulet/api/history/data_types.py
amulet/api/history/base/__init__.py
amulet/api/history/base/base_history.py
amulet/api/history/base/history_manager.py
amulet/api/history/base/revision_manager.py
amulet/api/history/history_manager/__init__.py
amulet/api/history/history_manager/container.py
amulet/api/history/history_manager/database.py
amulet/api/history/history_manager/meta.py
amulet/api/history/history_manager/object.py
amulet/api/history/revision_manager/__init__.py
amulet/api/history/revision_manager/disk.py
amulet/api/history/revision_manager/ram.py
amulet/api/level/__init__.py
amulet/api/level/structure.py
amulet/api/level/world.py
amulet/api/level/base_level/__init__.py
amulet/api/level/base_level/base_level.py
amulet/api/level/base_level/chunk_manager.py
amulet/api/level/base_level/clone.py
amulet/api/level/base_level/player_manager.py
amulet/api/level/immutable_structure/__init__.py
amulet/api/level/immutable_structure/immutable_structure.py
amulet/api/level/immutable_structure/void_format_wrapper.py
amulet/api/partial_3d_array/__init__.py
amulet/api/partial_3d_array/base_partial_3d_array.py
amulet/api/partial_3d_array/bounded_partial_3d_array.py
amulet_core-1.9.35.dist-info/licenses/LICENSE
amulet_core-1.9.35.dist-info/METADATA
amulet_core-1.9.35.dist-info/WHEEL
amulet_core-1.9.35.dist-info/entry_points.txt
amulet_core-1.9.35.dist-info/top_level.txt
amulet_core-1.9.35.dist-info/RECORD
