Metadata-Version: 2.4
Name: amulet-core
Version: 1.9.35
Summary: A Python library for reading/writing Minecraft's various save formats.
Home-page: https://www.amuletmc.com
Author: James Clare, Ben Gothard et al.
Author-email: amuleteditor@gmail.com
Platform: any
Classifier: Programming Language :: Python :: 3
Classifier: Operating System :: OS Independent
Requires-Python: >=3.9
License-File: LICENSE
Requires-Dist: numpy~=1.17
Requires-Dist: amulet-nbt~=2.0
Requires-Dist: pymctranslate~=1.2
Requires-Dist: portalocker~=2.4
Requires-Dist: amulet-leveldb~=1.0b0
Requires-Dist: platformdirs~=3.1
Requires-Dist: lz4~=4.3
Provides-Extra: docs
Requires-Dist: Sphinx>=1.7.4; extra == "docs"
Requires-Dist: sphinx-autodoc-typehints>=1.3.0; extra == "docs"
Requires-Dist: sphinx_rtd_theme>=0.3.1; extra == "docs"
Provides-Extra: dev
Requires-Dist: black~=26.1; extra == "dev"
Requires-Dist: pre_commit>=1.11.1; extra == "dev"
Dynamic: license-file
